{
  "invoice": {
    "isTaxInclusive": true,
    "lines": [
      {
        "id": "1",
        "itemId": "3",
        "units": "1",
        "description": "Large Cooler",
        "unitPrice": "1000",
        "discount": "0",
        "displayDiscount": "0",
        "taxCodeId": "1",
        "amount": "1000",
        "displayAmount": "1000.00"
      },
      {
        "id": "",
        "itemId": "4",
        "units": "3",
        "description": "Camp fridge",
        "unitPrice": "2000",
        "discount": "0",
        "displayDiscount": "0",
        "taxCodeId": "2",
        "amount": "2000",
        "displayAmount": "2000.00"
      }
    ]
  },
  "totals": {
    "displaySubTotal": "$2,000.00",
    "displayTotalTax": "$200.05",
    "displayTotalAmount": "$2,200.05",
    "displayAmountPaid": "$1000.00",
    "amountPaid": "1000.00",
    "displayAmountDue": "$1,200.05"
  }}
